speedtestpy
