Metadata-Version: 2.1
Name: speedtestpy
Version: 1.1.0
Summary: A module to easily get the speedtest data you need within seconds
Home-page: https://github.com/HYKANTUS/speedtestpy/
Author: HYKANTUS
Author-email: hykantus@gmail.com
License: UNKNOWN
Project-URL: Personal Website, http://hykantus.tk/
Keywords: speedtest,speedtest data,Developers
Platform: UNKNOWN
Classifier: Development Status :: 5 - Production/Stable
Classifier: Intended Audience :: Developers
Classifier: Topic :: Software Development :: Build Tools
Classifier: License :: OSI Approved :: MIT License
Classifier: Programming Language :: Python :: 3
Classifier: Programming Language :: Python :: 3.6
Classifier: Programming Language :: Python :: 3.7
Classifier: Programming Language :: Python :: 3.8
Classifier: Programming Language :: Python :: 3.9
Classifier: Programming Language :: Python :: 3 :: Only
Requires-Python: >=3.6, <4
